bdict/__init__.py
bdict-0.1.0.dist-info/METADATA
bdict-0.1.0.dist-info/RECORD
bdict-0.1.0.dist-info/WHEEL
bdict-0.1.0.dist-info/top_level.txt
