Metadata-Version: 2.1
Name: bdict
Version: 0.1.0
Summary: Python auto-binding dict
Home-page: https://github.com/bharel/bdict
Author: Bar Harel
Author-email: bzvi7919@gmail.com
License: UNKNOWN
Platform: UNKNOWN
Classifier: Programming Language :: Python :: 3
Classifier: Programming Language :: Python :: 3.5
Classifier: Programming Language :: Python :: 3.6
Classifier: Programming Language :: Python :: 3.7
Classifier: License :: OSI Approved :: MIT License
Classifier: Operating System :: OS Independent
Requires-Python: >=3.6
